_migmose_version.py
migmose/__init__.py
migmose/__main__.py
migmose/parsing.py
migmose/py.typed
migmose/mig/__init__.py
migmose/mig/nachrichtenstrukturtabelle.py
migmose/mig/nachrichtenstrukturzeile.py
migmose/mig/nestednachrichtenstruktur.py
migmose/mig/reducednestednachrichtenstruktur.py
migmose/mig/segmentgrouphierarchies.py
migmose-0.2.6.dist-info/METADATA
migmose-0.2.6.dist-info/WHEEL
migmose-0.2.6.dist-info/entry_points.txt
migmose-0.2.6.dist-info/licenses/LICENSE
migmose-0.2.6.dist-info/RECORD
