Metadata-Version: 2.3
Name: migmose
Version: 0.2.6
Summary: Tool to generate machine readable files from MIG documents
Project-URL: Changelog, https://github.com/Hochfrequenz/migmose/releases
Project-URL: Homepage, https://github.com/Hochfrequenz/migmose
Author-email: Kevin Krechan <kevin.krechan@hochfrequenz.de>
License: MIT
Keywords: automation,bdew,edi@energy,mig
Classifier: Development Status :: 4 - Beta
Classifier: Environment :: Console
Classifier: Intended Audience :: Developers
Classifier: License :: OSI Approved :: MIT License
Classifier: Operating System :: OS Independent
Classifier: Programming Language :: Python
Classifier: Programming Language :: Python :: 3 :: Only
Classifier: Programming Language :: Python :: 3.11
Classifier: Programming Language :: Python :: 3.12
Classifier: Programming Language :: Python :: 3.13
Requires-Python: >=3.11
Requires-Dist: click
Requires-Dist: efoli>=1.4.0
Requires-Dist: jinja2
Requires-Dist: loguru
Requires-Dist: pydantic
Requires-Dist: python-docx
Provides-Extra: coverage
Requires-Dist: coverage==7.6.9; extra == 'coverage'
Provides-Extra: formatting
Requires-Dist: black==24.10.0; extra == 'formatting'
Requires-Dist: isort==5.13.2; extra == 'formatting'
Provides-Extra: linting
Requires-Dist: pylint==3.3.2; extra == 'linting'
Provides-Extra: spellcheck
Requires-Dist: codespell==2.3.0; extra == 'spellcheck'
Provides-Extra: test-packaging
Requires-Dist: build==1.2.2.post1; extra == 'test-packaging'
Requires-Dist: twine==6.0.1; extra == 'test-packaging'
Provides-Extra: tests
Requires-Dist: maus[tree]==0.6.1; extra == 'tests'
Requires-Dist: pytest-loguru==0.4.0; extra == 'tests'
Requires-Dist: pytest==8.3.4; extra == 'tests'
Requires-Dist: syrupy==4.8.0; extra == 'tests'
Provides-Extra: type-check
Requires-Dist: mypy==1.13.0; extra == 'type-check'
